live_debugger/__init__.py
live_debugger/api.py
live_debugger/data.py
live_debugger/debugger.py
live_debugger/typing.py
live_debugger-0.1.0.dist-info/LICENSE
live_debugger-0.1.0.dist-info/WHEEL
live_debugger-0.1.0.dist-info/METADATA
live_debugger-0.1.0.dist-info/RECORD
