Metadata-Version: 2.1
Name: live-debugger
Version: 0.1.0
Summary: A simple library for CPython that allows you to collect stacktrace data from running processes in production environments without stopping the execution of the process.
Home-page: https://gitlab.com/yunier.rojas/python-live-debugger
License: AGPL-3.0
Keywords: python,live,debugger
Author: Yunier Rojas García
Author-email: yunier.rojas@gmail.com
Maintainer: Yunier Rojas García
Maintainer-email: yunier.rojas@gmail.com
Requires-Python: >=3.8,<4.0
Classifier: Development Status :: 3 - Alpha
Classifier: Intended Audience :: Developers
Classifier: License :: OSI Approved :: GNU Affero General Public License v3
Classifier: Programming Language :: Python :: 3
Classifier: Programming Language :: Python :: 3.8
Classifier: Programming Language :: Python :: 3.9
Classifier: Programming Language :: Python :: 3.10
Classifier: Programming Language :: Python :: 3.11
Classifier: Programming Language :: Python :: 3.10
Classifier: Programming Language :: Python :: 3.11
Classifier: Programming Language :: Python :: 3.8
Classifier: Programming Language :: Python :: 3.9
Classifier: Programming Language :: Python :: Implementation :: CPython
Project-URL: Documentation, https://python-live-debugger.readthedocs.io/en/latest/
Project-URL: Repository, https://gitlab.com/yunier.rojas/python-live-debugger
